{"/_app":"pages/_app.js","/create-account":"pages/create-account.html","/home":"pages/home.html","/_document":"pages/_document.js","/_error":"pages/_error.js","/login":"pages/login.html","/":"pages/index.html","/onboarding/start":"pages/onboarding/start.html","/onboarding/select-categories":"pages/onboarding/select-categories.html","/profile":"pages/profile.html","/onboarding/main-category":"pages/onboarding/main-category.html","/onboarding/sub-division":"pages/onboarding/sub-division.html","/questionnaire/[part]/[page]":"pages/questionnaire/[part]/[page].html","/start":"pages/start.html","/onboarding/sub-category":"pages/onboarding/sub-category.html","/terms-and-conditions":"pages/terms-and-conditions.html","/404":"pages/404.html"}